Metadata-Version: 1.1
Name: arr-ops
Version: 0.1
Summary: Useful library to operate arrays in a special way, other than the predetermined, oriented to mathematic matrixes
Home-page: https://github.com/Tester86/arr_ops
Author: Tester86
Author-email: tester86t@gmail.com
License: MIT
Download-URL: https://github.com/Tester86/arr_ops/arr_ops.py/v_01.tar.gz
Keywords: ARRAY,OPERATE,OPERATION,MATHEMATICS,MATH
Platform: UNKNOWN
Classifier: Development Status :: 4 - Beta
Classifier: Intended Audience :: Developers
Classifier: Topic :: Software Development :: Build Tools
Classifier: License :: OSI Approved :: MIT License
Classifier: Programming Language :: Python :: 3
Classifier: Programming Language :: Python :: 3.4
Classifier: Programming Language :: Python :: 3.5
Classifier: Programming Language :: Python :: 3.6
